torchutil/__init__.py
torchutil/checkpoint.py
torchutil/cuda.py
torchutil/download.py
torchutil/gradients.py
torchutil/inference.py
torchutil/iterator.py
torchutil/mask.py
torchutil/notify.py
torchutil/tensorboard.py
torchutil/time.py
torchutil/metrics/__init__.py
torchutil/metrics/background.py
torchutil/metrics/core.py
torchutil/metrics/utilization.py
torchutil/paths/__init__.py
torchutil/paths/core.py
torchutil/paths/gather/__init__.py
torchutil/paths/gather/core.py
torchutil/paths/measure/__init__.py
torchutil/paths/measure/__main__.py
torchutil/paths/measure/core.py
torchutil/paths/purge/__init__.py
torchutil/paths/purge/__main__.py
torchutil/paths/purge/core.py
torchutil-0.1.1.dist-info/LICENSE
torchutil-0.1.1.dist-info/METADATA
torchutil-0.1.1.dist-info/WHEEL
torchutil-0.1.1.dist-info/top_level.txt
torchutil-0.1.1.dist-info/RECORD
