Metadata-Version: 2.1
Name: torchutil
Version: 0.1.1
Summary: PyTorch utilities for developing deep learning frameworks
Author-email: Max Morrison <maxrmorrison@gmail.com>, Cameron Churchwell <cameronchurchwell@icloud.com>
License: MIT License
Project-URL: Homepage, https://github.com/maxrmorrison/torchutil
Project-URL: Issues, https://github.com/maxrmorrison/torchutil/issues
Classifier: License :: OSI Approved :: MIT License
Requires-Python: >=3.8
License-File: LICENSE
Requires-Dist: apprise
Requires-Dist: torch
Requires-Dist: tensorboard
Requires-Dist: tqdm
Requires-Dist: psutil
